django_doctor-2.6.0.dist-info/entry_points.txt
django_doctor-2.6.0.dist-info/WHEEL
django_doctor-2.6.0.dist-info/top_level.txt
django_doctor-2.6.0.dist-info/RECORD
django_doctor-2.6.0.dist-info/METADATA
django_doctor/__init__.py
django_doctor/staticanalysis/suggest.cpython-38-x86_64-linux-gnu.so
django_doctor/staticanalysis/checker.cpython-38-x86_64-linux-gnu.so
django_doctor/staticanalysis/diff.cpython-38-x86_64-linux-gnu.so
django_doctor/staticanalysis/helpers.cpython-38-x86_64-linux-gnu.so
django_doctor/staticanalysis/render.py
django_doctor/staticanalysis/__init__.py
django_doctor/staticanalysis/transformer.cpython-38-x86_64-linux-gnu.so
django_doctor/staticanalysis/meta.cpython-38-x86_64-linux-gnu.so
django_doctor/staticanalysis/constants.py
django_doctor/staticanalysis/shims.cpython-38-x86_64-linux-gnu.so
django_doctor/staticanalysis/message_templates.py
django_doctor/staticanalysis/dependencies.cpython-38-x86_64-linux-gnu.so
django_doctor/staticanalysis/checkers/templates.cpython-38-x86_64-linux-gnu.so
django_doctor/staticanalysis/checkers/urls.cpython-38-x86_64-linux-gnu.so
django_doctor/staticanalysis/checkers/settings.cpython-38-x86_64-linux-gnu.so
django_doctor/staticanalysis/checkers/admin.cpython-38-x86_64-linux-gnu.so
django_doctor/staticanalysis/checkers/migrations.cpython-38-x86_64-linux-gnu.so
django_doctor/staticanalysis/checkers/model_methods.cpython-38-x86_64-linux-gnu.so
django_doctor/staticanalysis/checkers/model_fields.cpython-38-x86_64-linux-gnu.so
django_doctor/staticanalysis/checkers/querysets.cpython-38-x86_64-linux-gnu.so
django_doctor/staticanalysis/library_default_settings/django_3_1.py
django_doctor/staticanalysis/library_default_settings/django_1_11.py
django_doctor/staticanalysis/library_default_settings/django_2_0.py
django_doctor/staticanalysis/library_default_settings/django_2_2.py
django_doctor/staticanalysis/library_default_settings/django_3_0.py
django_doctor/staticanalysis/library_default_settings/__init__.py
django_doctor/staticanalysis/library_default_settings/django_3_2.py
django_doctor/staticanalysis/library_default_settings/django_2_1.py
django_doctor/staticanalysis/commands/wsgi.py
