Metadata-Version: 2.1
Name: django_doctor
Version: 2.6.0
Summary: Find and fix Django mishaps.
Home-page: https://django.doctor
Author: Richard Tier
Author-email: help@django.doctor
License: Proprietary. Please purchase a license for commercial use.
Platform: UNKNOWN
Classifier: Development Status :: 5 - Production/Stable
Classifier: Environment :: Web Environment
Classifier: Framework :: Django
Classifier: Intended Audience :: Developers
Classifier: Natural Language :: English
Classifier: Operating System :: OS Independent
Classifier: Programming Language :: Python
Classifier: Topic :: Software Development :: Libraries :: Python Modules
Provides-Extra: test
